{
  "000000": {
    "label": "black",
    "hex": "000000",
    "codes": ["1D", "1E", "1F", "2C", "2G", "3B", "3H", "4A", "4C", "4I", "5A", "5D", "5I", "6B", "6C", "6J", "7B", "7K", "8A", "8L", "9B", "9K", "10B", "10E", "10H", "10K", "11B", "11K", "12B", "12K", "13B", "13K", "14C", "14J", "15D", "15I", "16E", "16H", "17F", "17G"]
  },
  "FF0000": {
    "label": "red",
    "hex": "FF0000",
    "codes": ["2D", "2E", "2F", "3C", "3D", "3E", "3F", "3G", "4D", "4E", "4F", "4G", "4H", "5E", "5F", "5G", "5H", "6D", "6E", "6F", "6G", "6H", "6I", "7C", "7D", "7E", "7F", "7G", "7H", "7I", "7J", "13E", "13H", "14F", "14G"]
  },
  "FFFF00": {
    "label": "yellow",
    "hex": "FFFF00",
    "codes": ["9D", "9E", "9F", "9G", "9H", "9I", "10D", "10F", "10G", "10I", "11D", "11E", "11F", "11G", "11H", "11I"]
  }
}
